test_versioning_repo_25_d/__init__.py
test_versioning_repo_25_d/example.py
test_versioning_repo_25_d/main.py
test_versioning_repo_25_d/resources/python-img.png
test_versioning_repo_25_d-1.2.0.dist-info/METADATA
test_versioning_repo_25_d-1.2.0.dist-info/WHEEL
test_versioning_repo_25_d-1.2.0.dist-info/entry_points.txt
test_versioning_repo_25_d-1.2.0.dist-info/licenses/LICENSE
test_versioning_repo_25_d-1.2.0.dist-info/RECORD
