Metadata-Version: 2.4
Name: test-versioning-repo-25-d
Version: 1.2.0
Summary: Test versioning
License-Expression: MIT
License-File: LICENSE
Requires-Python: >=3.12
